MANIFEST.in
setup.py
rest_framework/.DS_Store
rest_framework/__init__.py
rest_framework/log.py
rest_framework/__pycache__/__init__.cpython-36.pyc
rest_framework/__pycache__/log.cpython-36.pyc
rest_framework/bin/__init__.py
rest_framework/bin/tornado-admin.py
rest_framework/conf/__init__.py
rest_framework/conf/global_settings.py
rest_framework/conf/__pycache__/__init__.cpython-36.pyc
rest_framework/conf/__pycache__/global_settings.cpython-36.pyc
rest_framework/conf/templates/__init__.py
rest_framework/conf/templates/project/__init__.py
rest_framework/conf/templates/project/manage.py.tpl
rest_framework/conf/templates/project/settings.py.tpl
rest_framework/conf/templates/project/urls.py.tpl
rest_framework/core/__init__.py
rest_framework/core/application.py
rest_framework/core/codecs.py
rest_framework/core/datastructures.py
rest_framework/core/exceptions.py
rest_framework/core/pagination.py
rest_framework/core/request.py
rest_framework/core/response.py
rest_framework/core/router.py
rest_framework/core/singnals.py
rest_framework/core/translation.py
rest_framework/core/types.py
rest_framework/core/urls.py
rest_framework/core/validators.py
rest_framework/core/views.py
rest_framework/core/websockets.py
rest_framework/core/__pycache__/__init__.cpython-36.pyc
rest_framework/core/__pycache__/app.cpython-36.pyc
rest_framework/core/__pycache__/application.cpython-36.pyc
rest_framework/core/__pycache__/codecs.cpython-36.pyc
rest_framework/core/__pycache__/datastructures.cpython-36.pyc
rest_framework/core/__pycache__/exceptions.cpython-36.pyc
rest_framework/core/__pycache__/pagination.cpython-36.pyc
rest_framework/core/__pycache__/parsers.cpython-36.pyc
rest_framework/core/__pycache__/request.cpython-36.pyc
rest_framework/core/__pycache__/response.cpython-36.pyc
rest_framework/core/__pycache__/router.cpython-36.pyc
rest_framework/core/__pycache__/singnals.cpython-36.pyc
rest_framework/core/__pycache__/translation.cpython-36.pyc
rest_framework/core/__pycache__/types.cpython-36.pyc
tornado_rest_framework.egg-info/PKG-INFO
tornado_rest_framework.egg-info/SOURCES.txt
tornado_rest_framework.egg-info/dependency_links.txt
tornado_rest_framework.egg-info/entry_points.txt
tornado_rest_framework.egg-info/not-zip-safe
tornado_rest_framework.egg-info/requires.txt
tornado_rest_framework.egg-info/top_level.txt