Metadata-Version: 1.1
Name: tornado-rest-framework
Version: 1.0.9
Summary: Tornado Rest Framework
Home-page: https://github.com/caowenbin/tornado-rest-framework
Author: caowenbin
Author-email: cwb201314@qq.com
License: BSD
Download-URL: https://github.com/caowenbin/tornado-rest-framework
Keywords: tornado,asyncio,rest api,python3
Platform: UNKNOWN
Classifier: Programming Language :: Python :: 3.6
